sceneflow/__init__.py
sceneflow/_version.py
sceneflow/api/__init__.py
sceneflow/api/_internal.py
sceneflow/api/public.py
sceneflow/cli/__init__.py
sceneflow/cli/_internal.py
sceneflow/cli/app.py
sceneflow/core/__init__.py
sceneflow/core/ranker.py
sceneflow/core/scorer.py
sceneflow/detection/__init__.py
sceneflow/detection/energy_refiner.py
sceneflow/detection/speech_detector.py
sceneflow/extraction/__init__.py
sceneflow/extraction/extractor.py
sceneflow/extraction/face_metrics.py
sceneflow/integration/__init__.py
sceneflow/integration/airtable.py
sceneflow/selection/__init__.py
sceneflow/selection/llm_selector.py
sceneflow/shared/__init__.py
sceneflow/shared/config.py
sceneflow/shared/constants.py
sceneflow/shared/exceptions.py
sceneflow/shared/models.py
sceneflow/utils/__init__.py
sceneflow/utils/video.py
sceneflow-0.2.4.dist-info/METADATA
sceneflow-0.2.4.dist-info/WHEEL
sceneflow-0.2.4.dist-info/entry_points.txt
sceneflow-0.2.4.dist-info/licenses/LICENSE
sceneflow-0.2.4.dist-info/RECORD
