Metadata-Version: 2.4
Name: sceneflow
Version: 0.2.4
Summary: Smart video cut point detection for AI-generated talking head videos using multi-factor visual analysis and speech detection
Project-URL: Homepage, https://github.com/vertexcover-io/sceneflow
Project-URL: Documentation, https://github.com/vertexcover-io/sceneflow#readme
Project-URL: Repository, https://github.com/vertexcover-io/sceneflow.git
Project-URL: Issues, https://github.com/vertexcover-io/sceneflow/issues
Author-email: Aman Kumar Singh <aman@vertexcover.io>
License: MIT
License-File: LICENSE
Keywords: ai-video,computer-vision,cut-point,facial-landmarks,insightface,silero-vad,speech-detection,talking-head,vad,video,video-analysis,video-editing
Classifier: Development Status :: 4 - Beta
Classifier: Intended Audience :: Developers
Classifier: Intended Audience :: Science/Research
Classifier: License :: OSI Approved :: MIT License
Classifier: Operating System :: OS Independent
Classifier: Programming Language :: Python :: 3
Classifier: Programming Language :: Python :: 3.9
Classifier: Programming Language :: Python :: 3.10
Classifier: Programming Language :: Python :: 3.11
Classifier: Programming Language :: Python :: 3.12
Classifier: Topic :: Multimedia :: Video
Classifier: Topic :: Scientific/Engineering :: Artificial Intelligence
Classifier: Topic :: Scientific/Engineering :: Image Recognition
Requires-Python: >=3.9
Requires-Dist: cyclopts>=2.0.0
Requires-Dist: hatchling>=1.27.0
Requires-Dist: insightface>=0.7.3
Requires-Dist: librosa>=0.11.0
Requires-Dist: numpy>=1.24.0
Requires-Dist: onnxruntime>=1.20.1
Requires-Dist: openai>=1.0.0
Requires-Dist: opencv-python>=4.8.0
Requires-Dist: pyairtable>=3.2.0
Requires-Dist: requests>=2.31.0
Requires-Dist: silero-vad>=6.0.0
Requires-Dist: torch>=2.0.0
Provides-Extra: dev
Requires-Dist: black>=23.0.0; extra == 'dev'
Requires-Dist: mypy>=1.0.0; extra == 'dev'
Requires-Dist: pytest-cov>=4.0.0; extra == 'dev'
Requires-Dist: pytest>=7.0.0; extra == 'dev'
Requires-Dist: ruff>=0.1.0; extra == 'dev'
